{
  "generator-jhipster": {
    "applicationType": "monolith",
    "authenticationType": "oauth2",
    "baseName": "controlExpedientesBackend",
    "buildTool": "maven",
    "cacheProvider": "ehcache",
    "creationTimestamp": 1769279938427,
    "databaseType": "sql",
    "devDatabaseType": "postgresql",
    "enableHibernateCache": true,
    "enableTranslation": true,
    "entities": [],
    "feignClient": null,
    "jhipsterVersion": "8.11.0",
    "languages": ["es"],
    "nativeLanguage": "es",
    "packageName": "ni.edu.mney",
    "prodDatabaseType": "postgresql",
    "reactive": false,
    "serverPort": null,
    "serviceDiscoveryType": null,
    "skipClient": true,
    "skipUserManagement": true,
    "syncUserWithIdp": true,
    "testFrameworks": []
  }
}
